gmapFinder/__init__.py
gmapFinder/directions.py
gmapFinder-1.0.2.dist-info/LICENSE
gmapFinder-1.0.2.dist-info/METADATA
gmapFinder-1.0.2.dist-info/WHEEL
gmapFinder-1.0.2.dist-info/top_level.txt
gmapFinder-1.0.2.dist-info/RECORD
