Metadata-Version: 2.1
Name: gmapFinder
Version: 1.0.2
Summary: Gives the direction on Google Maps
Home-page: https://github.com/roshan9419/gmapFinder
Author: Roshan Kumar
Author-email: roshanthakur8571@gmail.com
License: MIT
Keywords: getDirection,getCurrentLocation
Platform: UNKNOWN
Classifier: Programming Language :: Python :: 3
Classifier: License :: OSI Approved :: MIT License
Classifier: Operating System :: OS Independent
Requires-Python: >=3.6
Requires-Dist: geopy
Requires-Dist: requests
